Workbook

Sheet Resumen
A1: Trabajo de grado 2026-2 - Propagadores con control de muestreo en DLHM
A3: Estudiante | B3: Camilo Rodriguez Londono | D3: COMO USAR ESTE ARCHIVO 1. La unica columna que se edita a diario es 'Estado' en la hoja Tareas (lista desplegable: Pendiente / En curso / Hecho / Bloqueado). 2. La hoja Cronograma calcula sola el avance de cada semana; no escribas en sus columnas de formula. 3. Usa la columna 'Notas' de la hoja Tareas para dejar constancia de bloqueos y decisiones. 4. Puedes agregar filas nuevas en Tareas hasta la fila 200 sin romper las formulas. SUPUESTO A VERIFICAR: se asume que la semana de receso es del 7 al 11 de septiembre. Las fechas institucionales confirmadas son semana 8 = 31 de agosto, semana 14 = 19 de octubre y entrega final = 30 de octubre; si el receso cae en otra semana, corre las fechas intermedias.
A4: Asesor principal | B4: Carlos Alejandro Trujillo Anaya, PhD
A5: Programa | B5: Ingenieria Fisica - Universidad EAFIT
A6: Modalidad de entrega | B6: Opcion 2 (grados de diciembre, sin mencion de honor)
A7: Entrega del informe final | B7: Viernes 30 de octubre de 2026 (semana 15)
A8: Defensa publica | B8: Hasta el viernes 20 de noviembre de 2026
A9: Ultima revision del plan | B9: Martes 1 de septiembre de 2026 (semana 8, dia 2)
A10: AVANCE GLOBAL
A11: Tareas totales | B11: =COUNTA(Tareas!$A$4:$A$200)
A12: Tareas completadas | B12: =COUNTIF(Tareas!$G$4:$G$200,"Hecho")
A13: Tareas en curso | B13: =COUNTIF(Tareas!$G$4:$G$200,"En curso")
A14: Tareas bloqueadas | B14: =COUNTIF(Tareas!$G$4:$G$200,"Bloqueado")
A15: Porcentaje completado | B15: =IFERROR(B12/B11,0)
A17: AVANCE POR FASE
A18: Fase | B18: Tareas | C18: Hechas
A19: Fase 1 - Implementacion | B19: =COUNTIF(Tareas!$C$4:$C$200,"F1") | C19: =COUNTIFS(Tareas!$C$4:$C$200,"F1",Tareas!$G$4:$G$200,"Hecho")
A20: Fase 2 - Calibracion numerica | B20: =COUNTIF(Tareas!$C$4:$C$200,"F2") | C20: =COUNTIFS(Tareas!$C$4:$C$200,"F2",Tareas!$G$4:$G$200,"Hecho")
A21: Fase 3 - Registro experimental | B21: =COUNTIF(Tareas!$C$4:$C$200,"F3") | C21: =COUNTIFS(Tareas!$C$4:$C$200,"F3",Tareas!$G$4:$G$200,"Hecho")
A22: Fase 4 - Comparacion y redaccion | B22: =COUNTIF(Tareas!$C$4:$C$200,"F4") | C22: =COUNTIFS(Tareas!$C$4:$C$200,"F4",Tareas!$G$4:$G$200,"Hecho")
A23: Hitos institucionales | B23: =COUNTIF(Tareas!$C$4:$C$200,"HITO") | C23: =COUNTIFS(Tareas!$C$4:$C$200,"HITO",Tareas!$G$4:$G$200,"Hecho")

Sheet Cronograma
A1: Cronograma semana a semana
A3: Semana | B3: Fechas | C3: Fase | D3: Foco de la semana | E3: Entregable de la semana | F3: Hito institucional | G3: Tareas | H3: Avance
A4: 4 | B4: 3 - 7 ago | C4: Fase 1 | D4: Reproducibilidad del codigo base | E4: Decision sobre el repositorio de Zhao | G4: =COUNTIF(Tareas!$B$4:$B$200,$A4) | H4: =IFERROR(COUNTIFS(Tareas!$B$4:$B$200,$A4,Tareas!$G$4:$G$200,"Hecho")/G4,0)
A5: 5 | B5: 10 - 14 ago | C5: Fase 1 | D5: FFT-ASM y BLAS bajo interfaz comun | E5: Dos propagadores verificados | G5: =COUNTIF(Tareas!$B$4:$B$200,$A5) | H5: =IFERROR(COUNTIFS(Tareas!$B$4:$B$200,$A5,Tareas!$G$4:$G$200,"Hecho")/G5,0)
A6: 6 | B6: 17 - 21 ago | C6: Fase 1 | D6: MPASM y verificacion analitica | E6: Objetivo 1 cerrado | G6: =COUNTIF(Tareas!$B$4:$B$200,$A6) | H6: =IFERROR(COUNTIFS(Tareas!$B$4:$B$200,$A6,Tareas!$G$4:$G$200,"Hecho")/G6,0)
A7: 7 | B7: 24 - 28 ago | C7: Fase 1 / 3 | D7: Montaje DLHM y parametros reales | E7: Hoja de parametros del montaje | G7: =COUNTIF(Tareas!$B$4:$B$200,$A7) | H7: =IFERROR(COUNTIFS(Tareas!$B$4:$B$200,$A7,Tareas!$G$4:$G$200,"Hecho")/G7,0)
A8: 8 | B8: 31 ago - 4 sep | C8: Hito | D8: Informe de avance 1 | E8: Exposicion (5 %) | F8: Informe de avance 1: 31 de agosto | G8: =COUNTIF(Tareas!$B$4:$B$200,$A8) | H8: =IFERROR(COUNTIFS(Tareas!$B$4:$B$200,$A8,Tareas!$G$4:$G$200,"Hecho")/G8,0)
A9: Receso | B9: 7 - 11 sep | C9: Receso | D9: Semana de receso (verificar calendario) | E9: Colchon del cronograma | G9: =COUNTIF(Tareas!$B$4:$B$200,$A9) | H9: =IFERROR(COUNTIFS(Tareas!$B$4:$B$200,$A9,Tareas!$G$4:$G$200,"Hecho")/G9,0)
A10: 9 | B10: 14 - 18 sep | C10: Fase 2 | D10: Iluminacion esferica en el esquema | E10: Pipeline DLHM validado en simulacion | G10: =COUNTIF(Tareas!$B$4:$B$200,$A10) | H10: =IFERROR(COUNTIFS(Tareas!$B$4:$B$200,$A10,Tareas!$G$4:$G$200,"Hecho")/G10,0)
A11: 10 | B11: 21 - 25 sep | C11: Fase 2 | D11: Barrido de parametros y mapas de error | E11: Objetivo 2 cerrado | G11: =COUNTIF(Tareas!$B$4:$B$200,$A11) | H11: =IFERROR(COUNTIFS(Tareas!$B$4:$B$200,$A11,Tareas!$G$4:$G$200,"Hecho")/G11,0)
A12: 11 | B12: 28 sep - 2 oct | C12: Fase 3 | D12: Registro experimental de hologramas | E12: Dataset documentado | G12: =COUNTIF(Tareas!$B$4:$B$200,$A12) | H12: =IFERROR(COUNTIFS(Tareas!$B$4:$B$200,$A12,Tareas!$G$4:$G$200,"Hecho")/G12,0)
A13: 12 | B13: 5 - 9 oct | C13: Fase 4 | D13: Reconstruccion y metricas comparativas | E13: Tabla comparativa completa | G13: =COUNTIF(Tareas!$B$4:$B$200,$A13) | H13: =IFERROR(COUNTIFS(Tareas!$B$4:$B$200,$A13,Tareas!$G$4:$G$200,"Hecho")/G13,0)
A14: 13 | B14: 12 - 16 oct | C14: Fase 4 | D14: Redaccion de resultados y analisis | E14: Borrador completo al asesor | G14: =COUNTIF(Tareas!$B$4:$B$200,$A14) | H14: =IFERROR(COUNTIFS(Tareas!$B$4:$B$200,$A14,Tareas!$G$4:$G$200,"Hecho")/G14,0)
A15: 14 | B15: 19 - 23 oct | C15: Hito | D15: Informe de avance 2 y correcciones | E15: Documento completo v1 | F15: Informe de avance 2: 19 de octubre | G15: =COUNTIF(Tareas!$B$4:$B$200,$A15) | H15: =IFERROR(COUNTIFS(Tareas!$B$4:$B$200,$A15,Tareas!$G$4:$G$200,"Hecho")/G15,0)
A16: 15 | B16: 26 - 30 oct | C16: Cierre | D16: Revision final y entrega | E16: Informe final + carta de aval | F16: ENTREGA FINAL: 30 de octubre | G16: =COUNTIF(Tareas!$B$4:$B$200,$A16) | H16: =IFERROR(COUNTIFS(Tareas!$B$4:$B$200,$A16,Tareas!$G$4:$G$200,"Hecho")/G16,0)

Sheet Tareas
A1: Lista de tareas - editar solo la columna Estado
A3: ID | B3: Semana | C3: Fase | D3: Tarea | E3: Entregable | F3: Prioridad | G3: Estado | H3: Fecha limite | I3: Notas
A4: 1 | B4: 4 | C4: F1 | D4: Consolidar correcciones y preguntas surgidas en la sustentacion | E4: Lista de ajustes acordados | F4: Alta | G4: Hecho | H4: 07/08/2026 | I4: CERRADA el 31/08. Los ajustes acordados en la sustentacion se responden en el material del avance 1. Estuvo abierta 24 dias mas alla de su fecha (07/08): es la tarea que mas tiempo llevo sin cerrar.
A5: 2 | B5: 4 | C5: F1 | D5: Clonar repositorio Figshare (Zhao 2020) y montar entorno Python | E5: Entorno reproducible | F5: Alta | G5: Hecho | H5: 07/08/2026
A6: 3 | B6: 4 | C6: F1 | D6: Reproducir la Figura 4 del paper con el codigo publicado | E6: Notebook de reproduccion | F6: Alta | G6: Hecho | H6: 07/08/2026 | I6: CERRADA el 23/08 (commit ea3a7a8). scripts/exactitud.py hace un solo barrido de 30 distancias -las siete de la tabla del paper mas una rejilla logaritmica entre ellas- y escribe resultados/exactitud/sam_vs_z.csv y sam_vs_z.png. La curva es la reproduccion de la Figura 4: MPASM entre 31 y 48 dB en todo el rango, FFT-ASM cayendo hasta -1.85 dB y BL-ASM degradandose y recuperandose cuando su mascara empieza a actuar. La vertical de la figura marca los 11.4 m a los que el radio 1/e del haz llena la ventana, que es donde FFT-ASM se desploma. Reproducida con CamposT, no con el codigo publicado: ese camino se cerro en la tarea 4 (port propio) y el contraste contra terceros vive en la tarea 58.
A7: 4 | B7: 4 | C7: F1 | D7: Documentar discrepancias y decidir si se reutiliza el codigo | E7: Decision go / no-go | F7: Alta | G7: Hecho | H7: 07/08/2026 | I7: Decidido: port propio a CamposT/propagadores.py en vez de reutilizar el codigo publicado. Se corrigio la Ec. (14): el codigo original usa A**2 * B donde el paper dice A**2 + B (ver kf_auto, formula='codigo' reproduce el bug).
A8: 5 | B8: 4 | C8: F1 | D8: Acordar con el asesor la agenda de reuniones semanales | E8: Agenda fijada | F8: Media | G8: Hecho | H8: 07/08/2026
A9: 6 | B9: 5 | C9: F1 | D9: Definir la interfaz comun del modulo (firma unica de propagacion) | E9: Especificacion de API | F9: Alta | G9: Hecho | H9: 14/08/2026 | I9: Hecha. La interfaz comun es pipeline.propagar(U0, delta, lamb, z, metodo, pad, device, dtype) -> (campo, info), uniforme para los tres metodos. Las funciones de bajo nivel conservan su retorno propio a proposito: mpasm devuelve Kf porque es un resultado del metodo, no un detalle de implementacion.
A10: 7 | B10: 5 | C10: F1 | D10: Implementar FFT-ASM | E10: Propagador funcional | F10: Alta | G10: Hecho | H10: 14/08/2026 | I10: CamposT/propagadores.py, fft_asm(). Revisado el 23/08 (commit c5fd678): aplica la transferencia in situ en vez de materializar H y multiplicar, que pedia dos arrays del tamano del plano de mas. Bit a bit identico, +4 % CPU y +7.6 % GPU. Corregido otra vez en la semana 7: ver tarea 66 (la rejilla de frecuencias estaba medio paso corrida en malla impar).
A11: 8 | B11: 5 | C11: F1 | D11: Implementar BLAS (espectro angular de banda limitada) | E11: Propagador funcional | F11: Alta | G11: Hecho | H11: 14/08/2026 | I11: CamposT/propagadores.py, blas() - Matsushima & Shimobaba (2009). Revisado el 23/08 (commit c5fd678): el limite de banda es un rectangulo centrado, asi que se anulan las cuatro bandas de fuera por rodajas en vez de construir H, dos meshgrid y una mascara. Bit a bit identico, +8.3 % CPU y +17.4 % GPU, y 1.6 GB menos de picos sobre una malla de 6000x8000. Corregido otra vez en la semana 7: ver tarea 66 (la misma rejilla medio paso corrida que fft_asm).
A12: 9 | B12: 5 | C12: F1 | D12: Tests unitarios: energia, caso z=0, reversibilidad | E12: Suite de tests | F12: Media | G12: Hecho | H12: 14/08/2026 | I12: tests/test_propagadores.py + tests/conftest.py. Cubre z=0, energia, reversibilidad, MPASM con Kf>1, paridad CPU/GPU, kf_auto y la funcion de transferencia. Validada por mutacion: 6 bugs inyectados, 6 detectados. Correr con: python -m pytest La suite fue creciendo con el paquete: 119 casos al crearse, 186 y 213 el 23/08 (retropropagacion y pipeline). AL 31/08 VA POR 299 CASOS EN VERDE en 56 s: los nuevos vienen de la rejilla centrada (16, tarea 66), el modo mixto, las fases de la retropropagacion, la nitidez, el pico de foco y la intensidad sin gamma. CERRADO el 01/09 lo de tests/mi_test.py (tarea 72): no costaba 12.2 s, COLGABA la recoleccion. Movido a scripts/, la suite pasa de 56 s a 38.29 s con los mismos 299 casos en verde.
A13: 10 | B13: 5 | C13: F1 | D13: Configurar repositorio git y estructura de paquete | E13: Repo inicializado | F13: Media | G13: Hecho | H13: 14/08/2026 | I13: Commit 3ef0cfa: paquete CamposT/ + scripts/ + referencia/ + resultados/. README con estructura y modo de ejecucion.
A14: 11 | B14: 6 | C14: F1 | D14: Implementar MPASM con parametros s y Kf explicitos | E14: Propagador funcional | F14: Alta | G14: Hecho | H14: 21/08/2026 | I14: Adelantada. CamposT/propagadores.py, mpasm() con s, Kf, r y mag explicitos y kf_auto() para el Kf automatico. Corregido despues, en la semana 6: ver tarea 63 (Kf a z < 0 y guardia de ventana de salida).
A15: 12 | B15: 6 | C15: F1 | D15: Implementar Rayleigh-Sommerfeld 1D como referencia numerica | E15: Referencia de verificacion | F15: Alta | G15: Hecho | H15: 21/08/2026 | I15: Hecha. CamposT/referencias.py, rs1_radial(): R-S I exacta reducida a 1-D por simetria circular (el paper dice que reduce el calculo 2-D a 1-D pero no como; es reescribir la integral en polares, sin aproximar). O(N_rho^2 N_phi) en vez de O(N^4): la fuerza bruta de pyLHM tardaria 1-2 h en la malla de la Tabla 1. Contrastada contra esa fuerza bruta y 19x mas exacta que ella (1.0e-3 frente a 1.9e-2 contra la analitica). No es paraxial, asi que su diferencia con gauss_analytic mide la paraxialidad. 11 tests, mutacion 8/8.
A16: 13 | B16: 6 | C16: F1 | D16: Verificacion contra propagacion analitica de haz gaussiano | E16: Curvas de error | F16: Alta | G16: Hecho | H16: 21/08/2026 | I16: CERRADA el 23/08 (commit ea3a7a8). Era el mismo entregable que la tarea 3 y sale de la misma figura: las curvas de error contra el gaussiano analitico, con SAM y no con RMS. Quedan las DOS referencias independientes -gauss_analytic, paraxial, y rs1_radial, no paraxial- mas la metrica del paper y su barrido graficado.
A17: 14 | B17: 6 | C17: F1 | D17: Implementar metrica SAM y generar curvas SAM vs z | E17: Graficas SAM | F17: Alta | G17: Hecho | H17: 21/08/2026 | I17: Hecha. CamposT/metricas.py, sam(). ERRATA ENCONTRADA en la Ec. (16): el denominador impreso es integral I_ref y tiene que ser integral I_ref^2. Con la impresa, un campo identico a su referencia da 0.365 dB en vez de infinito y el SAM queda bajo 2.5 dB para todo, o sea que el paper no habria podido generar su propia Figura 4. Segunda errata, tras el A^2*B de la Ec. (14). sam(formula='literal') reproduce la impresa. Al 23/08 su entregable -las graficas SAM- ya existe de verdad: resultados/exactitud/sam_vs_z.png (tarea 3). Y la metrica se endurecio (commit 61e7e1a) contra tres casos degenerados que devolvian un numero creible: un campo nulo daba +inf, o sea el mejor valor posible, porque la Ec. (15) queda 0/0 y la rama del residuo no miraba el numerador; una referencia nula daba NaN con un aviso de NumPy; y dos mallas distintas se difundian en silencio, que es facil de encontrarse porque rs1_radial devuelve perfiles radiales. 15 tests.
A18: 15 | B18: 6 | C18: F1 | D18: Redactar seccion de metodologia: implementacion (Obj. 1) | E18: Borrador de seccion | F18: Media | G18: Pendiente | H18: 21/08/2026 | I18: SIN EMPEZAR el 31/08, diez dias despues de vencer. Las diapositivas del avance 1 salieron sin ella. El material esta escrito pero disperso -el README, los docstrings del paquete y las notas de este cronograma-: falta pasarlo a prosa de tesis, y a partir de hoy compite con la Fase 2. Es la primera deuda de escritura del proyecto. AL 01/09 SIGUE SIN EMPEZAR y queda fuera del foco de la semana 8 y del receso, que se dedican a la tarea 17, a la Fase 2 (24-26) y a la limpieza del repo. Se arrastra a la semana 9, donde ya compite con F2. Es la segunda vez que se aplaza.
A19: 16 | B19: 7 | C19: F3 | D19: Sesion de familiarizacion con el montaje DLHM | E19: Bitacora de laboratorio | F19: Alta | G19: Hecho | H19: 28/08/2026 | I19: Hecha en la semana 7. Queda pendiente lo que tenia que salir de ella: los parametros reales del montaje (tarea 17).
A20: 17 | B20: 7 | C20: F3 | D20: Levantar parametros reales: lambda, pitch, sensor, L, z, NA | E20: Hoja de parametros | F20: Alta | G20: En curso | H20: 28/08/2026 | I20: VENCIDA el 28/08 y abierta al 31/08. Es la dependencia mas critica del cronograma: la Fase 2 arranca el 14/09 -dos semanas, con el receso de por medio- y sin lambda, pitch, sensor, L, z y NA reales el barrido de la tarea 30 se corre sobre valores inventados y hay que repetirlo. El acceso al montaje ya no es el bloqueo: la sesion de familiarizacion (tarea 16) y la reserva de laboratorio (tarea 18) estan hechas. AL 01/09 ES EL FOCO DE LA SEMANA 8: quedan cuatro dias habiles (1-4 sep) antes del receso, y despues del receso solo queda la semana del 14/09, que es cuando arranca la Fase 2 que depende de estos numeros. Al 01/09 su entregable esta PREPARADO Y VACIO (tarea 73): docs/hoja_parametros_montaje.md es el checklist que se lleva al laboratorio y CamposT/montaje.py el destino de los numeros. Faltan los 15 valores; cualquier cuenta que use uno de ellos falla en el acto en vez de propagar un valor inventado. CONFIRMADO el 01/09 que hay acceso al montaje esta misma semana, asi que la tarea deja de depender de la reserva de las semanas 9 a 11. EN CURSO desde el 20/09 (commit 4e0927c0e): montaje.py tiene ya lambda, pinhole, los dos pasos de pixel y L medidos, 5 de los 15 parametros. Quedan 10 pendientes.
... A25: 22 | B25: 8 | C25: HITO | D25: Registrar retroalimentacion y ajustar el plan | E25: Plan actualizado | F25: Media | G25: Hecho | H25: 31/08/2026 | I25: CERRADA el 01/09. La retroalimentacion del avance 1 no trajo ajustes al cronograma, asi que el plan sigue vigente sin cambios. Lo que decide el arranque de la Fase 2 no es esta retroalimentacion sino la tarea 17, que sigue vencida.
A26: 23 | B26: Receso | C26: BUF | D26: Semana de receso: recuperar tareas atrasadas o lectura pendiente | E26: Colchon del cronograma | F26: Baja | G26: Pendiente | H26: 11/09/2026
A27: 24 | B27: 9 | C27: F2 | D27: Formular la adaptacion a iluminacion esferica divergente | E27: Desarrollo teorico | F27: Alta | G27: Hecho | H27: 25/09/2026 | I27: Adelantada. figura_escenario.py (commit c6963d1) fija la primitiva: la lente f = -300 mm de la Tabla 1, aplicada sobre la cintura, deja el haz con R = 300 mm y la cintura intacta, o sea un pinhole virtual. Se modela el frente esferico divergente, no la lente. Falta pasar de la figura al desarrollo escrito. Reunion con el asesor el 08/09 (docs/reunion_asesor.pdf): la fecha limite se corrio al 25/09 (fin de semana 10). CERRADA el 22/09: docs/tarea24_mpasm_onda_esferica.pdf es el desarrollo escrito que faltaba, sobre la onda esferica en MPASM.
A28: 25 | B28: 9 | C28: F2 | D28: Implementar compensacion de fase y magnificacion geometrica | E28: Codigo funcional | F28: Alta | G28: Hecho | H28: 18/09/2026 | I28: La magnificacion geometrica ya existe: parametro mag de mpasm (r1, r2 de las Ecs. (7)-(8)), verificado en figura_escenario.py con malla de salida 6x. Falta la compensacion de fase de la iluminacion divergente. CERRADA el 27/09 con la tarea 78 (commit 17b6e2f510), fuera de su fecha del 18/09. La compensacion de fase de la iluminacion divergente es la esferica EXACTA e^{ikr}/r, en los dos sentidos y sin aproximacion paraxial: al reconstruir se multiplica por la de la fuente vista en el sensor (R = L) y se divide por la vista en la muestra (R = z); su parte parabolica va dentro de las matrices de la DFT del MPASM y el residuo punto a punto. La magnificacion geometrica M = L/z es exacta (proyeccion central entre planos paralelos) y entra como la malla de la muestra, delta*z/L, sin reescalar nada. Verificado contra Rayleigh-Sommerfeld directo: 3.6e-6 de error relativo hasta 12.4 grados.
A29: 26 | B29: 9 | C29: F2 | D29: Montar el pipeline de reconstruccion DLHM con los 4 propagadores | E29: Pipeline unificado | F29: Alta | G29: En curso | H29: 18/09/2026 | I29: Empezada por su mitad general: CamposT/retropropagacion.py (tarea 64) ya reconstruye sobre un barrido de z con los tres propagadores del paquete, pero asume iluminacion colimada. Al 31/08 se suma scripts/retro_holograma.py (tarea 67), que retropropaga un holograma ya registrado llamando a pipeline.propagar(), con los tres propagadores sobre el mismo dato y la misma z. Falta lo especifico de DLHM: la fuente puntual divergente (magnificacion M = L/z y distancia efectiva, tarea 24) y el cuarto propagador.
A30: 27 | B30: 9 | C30: F2 | D30: Validar con holograma simulado de muestra sintetica | E30: Reconstruccion simulada | F30: Alta | G30: Hecho | H30: 18/09/2026 | I30: ADELANTADA (era semana 9). Validacion de extremo a extremo sobre DLHM-model: holograma simulado con verdad-terreno conocida, retropropagado con MPASM. La fase reconstruida a la distancia nominal devuelve el target con los grupos de barras USAF y sus numeros legibles, sin ajustar parametros. Dos lecciones: el caso cae FUERA del rango de FFT-ASM (z_lim = 6.6 mm frente a z = 24 mm), y el criterio de autofoco depende del tipo de objeto (en fase hay que MINIMIZAR la varianza de amplitud, no maximizar nitidez). Falta versionarlo como scripts/reconstruccion_dlhm.py. Al 23/08 la maquinaria de retropropagacion ya esta versionada (tarea 64), asi que lo que queda es rehacer esa validacion llamando al paquete en vez del script suelto. CERRADA el 27/09 con la tarea 78 (commit 17b6e2f510), fuera de su fecha del 18/09. La validacion ya llama al paquete (CamposT.dlhm) y queda versionada como scripts/verif_dlhm_esferico.py, no como scripts/reconstruccion_dlhm.py. Hologramas simulados con la ida exacta (3.6e-6 contra RS directo) de dos muestras sinteticas con verdad-terreno: un mosaico de detalle de ~1.25 um, reconstruido con corr 0.969 en la ventana entera del sensor de 3000 px (1.0000 hasta 3 grados), y el BenchmarkTarget de DLHM-model a z = 3 mm, del que un barrido por nitidez sobre el holograma de INTENSIDAD recupera z = 3.0005 mm sin conocer el objeto. La imagen gemela sigue sin suprimirse (corr 0.95 en el centro con intensidad, 1.000 con el campo complejo).
A31: 28 | B31: 9 | C31: F2 | D31: Redactar seccion: propagacion bajo iluminacion esferica | E31: Borrador de seccion | F31: Media | G31: Pendiente | H31: 18/09/2026
A32: 29 | B32: 10 | C32: F2 | D32: Definir la malla del barrido de parametros (z, NA, s, Kf) | E32: Diseno del barrido | F32: Alta | G32: Pendiente | H32: 25/09/2026
A33: 30 | B33: 10 | C33: F2 | D33: Ejecutar el barrido y generar los mapas de error | E33: Mapas de validez | F33: Alta | G33: Pendiente | H33: 25/09/2026
A34: 31 | B34: 10 | C34: F2 | D34: Derivar el criterio operativo de seleccion de s y Kf | E34: Criterio documentado | F34: Alta | G34: En curso | H34: 25/09/2026 | I34: Primer criterio duro ya derivado, y metido en el codigo en vez de solo documentado: r*mag <= s*Kf (mpasm._comprobar_ventana, tarea 63). Sale de que el espectro, muestreado cada 1/(s*N*delta*Kf), describe un campo que se repite cada s*N*delta*Kf, mientras la malla de salida abarca r*N*delta*mag. Falta el criterio de eleccion de s y Kf frente a z y NA, que es lo que dara el barrido de la tarea 30.
A35: 32 | B35: 10 | C35: F2 | D35: Contrastar MPASM y CZT termino a termino | E35: Nota tecnica | F35: Media | G35: En curso | H35: 25/09/2026 | I35: Contraste parcial hecho: scripts/contraste_referencias.py compara CamposT contra pyDHM (angularSpectrum y bluestein/CZT). fft_asm coincide con pyDHM.angularSpectrum a 1e-8. Falta el contraste termino a termino MPASM vs CZT. Se suma scripts/retro_fft_angular.py: la ida y vuelta con el angularSpectrum de pyDHM tal cual, en una sola pieza y sin importar CamposT, como contraste independiente del paquete. Deja medidos dos defectos del original: dfx y dfy cruzados (irrelevante en malla cuadrada, 2.95e-1 de error contra el gaussiano analitico en malla rectangular) y las evanescentes dejadas decaer, que al RETROPROPAGAR crecen en vez de decaer. Al 23/08 se suma retro_mpasm.py (tarea 65), que contrasta MPASM contra el original de Zhao termino a termino y da 0.000e+00 en doble precision. No cierra esta tarea: lo que sigue pendiente es el contraste contra la CZT de pyDHM, que es otro metodo y no otra implementacion del mismo.
A36: 33 | B36: 10 | C36: F2 | D36: Redactar seccion: calibracion numerica (Obj. 2) | E36: Borrador de seccion | F36: Media | G36: Pendiente | H36: 25/09/2026
A37: 34 | B37: 11 | C37: F3 | D37: Alineacion del montaje y verificacion de estabilidad | E37: Montaje alineado | F37: Alta | G37: Pendiente | H37: 02/10/2026
A38: 35 | B38: 11 | C38: F3 | D38: Registro de hologramas del target USAF 1951 a dos o mas magnificaciones | E38: Hologramas USAF | F38: Alta | G38: Pendiente | H38: 02/10/2026
A39: 36 | B39: 11 | C39: F3 | D39: Registro de muestra micrometrica o biologica | E39: Hologramas de muestra | F39: Media | G39: Pendiente | H39: 02/10/2026
A40: 37 | B40: 11 | C40: F3 | D40: Capturar referencias sin muestra y ruido de fondo | E40: Imagenes de referencia | F40: Alta | G40: Pendiente | H40: 02/10/2026
A41: 38 | B41: 11 | C41: F3 | D41: Organizar el dataset con metadatos y respaldo | E41: Dataset documentado | F41: Alta | G41: Pendiente | H41: 02/10/2026
A42: 39 | B42: 12 | C42: F4 | D42: Reconstruir todo el dataset con los 4 propagadores | E42: Reconstrucciones completas | F42: Alta | G42: Pendiente | H42: 09/10/2026
A43: 40 | B43: 12 | C43: F4 | D43: Medir resolucion lateral efectiva sobre el target USAF | E43: Tabla de resolucion | F43: Alta | G43: Pendiente | H43: 09/10/2026
A44: 41 | B44: 12 | C44: F4 | D44: Medir contraste, relacion senal-ruido y tiempo de computo | E44: Tabla de metricas | F44: Alta | G44: Pendiente | H44: 09/10/2026
A45: 42 | B45: 12 | C45: F4 | D45: Consolidar la tabla comparativa de resultados | E45: Tabla final | F45: Alta | G45: Pendiente | H45: 09/10/2026
A46: 43 | B46: 12 | C46: F4 | D46: Generar las figuras finales de resultados | E46: Figuras | F46: Alta | G46: Pendiente | H46: 09/10/2026
A47: 44 | B47: 13 | C47: F4 | D47: Redactar el capitulo de resultados | E47: Capitulo completo | F47: Alta | G47: Pendiente | H47: 16/10/2026
... A59: 56 | B59: 15 | C59: HITO | D59: Entregar el informe final con carta de aval (30 de octubre) | E59: ENTREGA FINAL | F59: Alta | G59: Pendiente | H59: 30/10/2026
A60: 57 | B60: 5 | C60: F1 | D60: Benchmark CPU vs GPU: escalado con N y con el sobremuestreo s | E60: Curvas de tiempo y aceleracion | F60: Alta | G60: Hecho | H60: 14/08/2026 | I60: scripts/comparacion.py -> resultados/tiempos.png, aceleracion.png, escalado_N.csv, escalado_s.csv. Separa la aceleracion por hardware (x) de la aceleracion a igual precision (x_iso) y reporta la fraccion del tiempo que se va en transferencias.
A61: 58 | B61: 5 | C61: F1 | D61: Parchar los repos de referencia y contrastar CamposT contra pyDHM | E61: Script de parches + tabla de contraste | F61: Media | G61: Hecho | H61: 14/08/2026 | I61: Commit 8aa0403. parchar_referencias.py: ocho parches idempotentes, ninguno cambia la fisica, con marca [parche TG] en cada linea tocada. contraste_referencias.py: fft_asm coincide con pyDHM.angularSpectrum a 1e-8.
A62: 59 | B62: 6 | C62: F1 | D62: Reproducir el escenario de la Tabla 1 (apertura y frente propagado) | E62: Figura del escenario | F62: Media | G62: Hecho | H62: 21/08/2026 | I62: Commit c6963d1, repartida en tres figuras por el commit 641861a: scripts/figura_escenario.py -> resultados/escenario/apertura.png, frente_propagado.png y corte_axial.png. Insumo de la tarea 24: es donde se resuelve que la lente del paper es un pinhole virtual.
A63: 60 | B63: 6 | C63: F1 | D63: Corregir el factor 2 en la conversion del target USAF a lp/mm | E63: Geometria contrastada contra la imagen | F63: Alta | G63: Hecho | H63: 21/08/2026 | I63: periodos_usaf devolvia el ancho de barra llamandolo periodo. Un par de lineas es barra+hueco = 2b, asi que toda cifra de resolucion habria salido con factor 2. Alimenta directamente la tarea 40. Ahora anchos_barra_usaf / periodos_usaf / lineas_por_mm_usaf salen de una sola fuente, la misma con la que dibuja usaf_like.
A64: 61 | B64: 6 | C64: F1 | D64: Calcular K_fx y K_fy por eje para campos no cuadrados | E64: Propagador correcto en malla rectangular | F64: Alta | G64: Hecho | H64: 21/08/2026 | I64: La Tabla 1 los lista por separado y mpasm usaba uno solo. Kf va como ~1/sqrt(N), asi que el eje corto quedaba submuestreado en silencio. Con un target USAF en malla 64x128 el error es 5x a 63x mayor; con un gaussiano NO se aprecia, porque hace falta contenido cerca del limite de banda para que aparezca aliasing. Los sensores de DLHM no son cuadrados: esto habria aparecido en la semana 11.
A65: 62 | B65: 6 | C65: F1 | D65: Separar el paquete por responsabilidad (referencias, metricas, pipeline) | E65: Paquete navegable | F65: Media | G65: Hecho | H65: 21/08/2026 | I65: propagadores.py habia llegado a 539 lineas con cuatro asuntos dentro y campos.py mezclaba construir el campo con propagarlo y guardarlo. Ahora seis modulos de un tema cada uno, ninguno de mas de 235 lineas: campos, propagadores, referencias, metricas, pipeline y backend. 158 tests en verde antes y despues: el comportamiento no cambio.
A66: 63 | B66: 6 | C66: F1 | D66: Corregir Kf a distancia negativa y comprobar la ventana de salida de MPASM | E66: Propagador correcto al retropropagar | F66: Alta | G66: Hecho | H66: 21/08/2026 | I66: Commit f166a17. kf_auto aplicaba la Ec. (14) tal cual a z < 0, donde fmax sale negativo y el max(1.0, ...) devuelve 1: la compresion quedaba apagada y MPASM corria como un FFT-ASM rellenado de ceros en TODA retropropagacion, sin avisar. Kf depende de |z| y no de z, porque H(-z) = conj(H(z)). Error contra la referencia a 400 mm: de 5.4 a 1.1e-2. Ademas _comprobar_ventana aborta si r*mag > s*Kf; antes esa violacion devolvia copias periodicas del campo superpuestas, con error relativo 1.0 contra el gaussiano analitico y sin fallar ni avisar. Ese limite es el primer criterio operativo de la tarea 31. De 177 a 186 tests.
A67: 64 | B67: 6 | C67: F2 | D67: Retropropagacion de hologramas: modulo, CLI y suite de verificacion | E67: Reconstruccion sobre un barrido de z | F67: Alta | G67: Hecho | H67: 21/08/2026 | I67: ADELANTADA: es la mitad general de la tarea 26 (semana 9). CamposT/retropropagacion.py carga la imagen como INTENSIDAD medida (load_field mode='holograma', U = sqrt(I)), propaga a -z con los tres propagadores sobre un barrido de distancias y escribe resultados/retropropagacion/<holograma>/<metodo>/. CLI 'python -m CamposT.retropropagacion' y scripts/mi_holograma.py con constantes editables, que llama a su main() para que no puedan divergir. 19 tests: la reconstruccion RE-LOCALIZA el objeto (del 0.10 % al 7.5 % del contraste sobre una huella que es el 0.39 % del plano) y queda escrito que el signo NO se puede verificar sobre la intensidad, porque con entrada real |U(-z)|^2 = |U(+z)|^2 (medido: 3.5e-16): es la ambiguedad de la imagen gemela. Dos limites declarados: iluminacion colimada, sin la correccion de fuente puntual de DLHM, y sin supresion de la gemela. Commit b916792.
A68: 65 | B68: 6 | C68: F1 | D68: Completar la serie de ida y vuelta: un script suelto por propagador | E68: Contraste independiente del paquete | F68: Media | G68: Hecho | H68: 21/08/2026 | I68: Commit 439394b. retro_blas.py y retro_mpasm.py completan lo que retro_fft_angular.py empezo: la misma ida y vuelta (objeto a +z, holograma, vuelta a -z) en una pieza que se lee entera, una por propagador y sin importar CamposT. Verificado por dos caminos. Uno: donde los tres metodos coinciden por construccion tienen que dar lo mismo, y a Z = 100 mm sobre BenchmarkTarget reducido a 512 px -mascara de BL-ASM inactiva y Kf = 1- los tres devuelven +0.9404 de correlacion en la vuelta A y +0.7730 en la B, y enfocan en la misma z. Dos: contra algo ya verificado, el BL-ASM del script da 0.000e+00 contra el blas de CamposT en malla cuadrada y rectangular y en los dos signos de z, y el MPASM da 0.000e+00 contra el original de Zhao en CPU complex128 (7.67e-07 en GPU complex64, que es la mantisa). retro_mpasm.py lleva el MatrixDftCPU de Zhao copiado tal cual y enseña sus dos erratas corriendo: a Z = 2000 mm imprime Kf = 2.013 por el A^2*B contra 1.305 por el A^2+B del paper, y Kf = 1.000 a z = -2000 mm, o sea la compresion apagada en toda retropropagacion (el bug de la tarea 63, visto en el codigo publicado). retro_blas.py no lleva referencia de terceros porque no la hay: pyDHM trae fresnel, bluestein y angularSpectrum y ninguno limita la banda. DOS HALLAZGOS para el documento: comprimir tambien es descartar -Kf > 1 estrecha el rango muestreado a +-1/(2*delta*Kf) y lo de fuera no vuelve, asi que MPASM con compresion NO es reversible: +0.662 de correlacion a Z = 2000 mm, practicamente lo mismo que BL-ASM ahi (+0.662), la misma perdida por dos caminos-; y el barrido de foco sale sesgado hacia distancias cortas en los dos metodos, porque la banda util cae con z a la vez que la nitidez, lo que alimenta el criterio de autofoco de la tarea 27.
A69: 66 | B69: 7 | C69: F1 | D69: Centrar la rejilla de frecuencias con fftfreq en FFT-ASM y BL-ASM | E69: Propagadores correctos en malla impar | F69: Alta | G69: Hecho | H69: 28/08/2026 | I69: Commit 93bd392. Los dos construian la rejilla como (arange(n) - n/2)/(delta*n) y la emparejaban con fftshift, que deja la componente continua en el indice n//2: esa expresion vale 0 ahi SOLO SI n ES PAR. Con n impar la rejilla queda medio paso corrida, H se evalua fuera de sitio y el campo propagado sale desplazado lambda*z*(0.5/(delta*n))/delta pixeles. Medido contra el gaussiano analitico en malla 65x65: RMS 4.2e-2 antes y 5.5e-4 despues; en 64x64 las dos rejillas coinciden hasta el ultimo bit, asi que esto NO puede mover ningun resultado anterior. El fallo era MUDO: el medio paso se aplica en la ida y otra vez en la vuelta y se cancela, asi que ninguna prueba de reversibilidad podia verlo y hubo que contrastar contra una solucion analitica. mpasm no lo tenia -construye su rejilla junto con las matrices de la DFT, sin fftshift de por medio-. Ahora frecuencias_fft(n, delta) es la unica fuente para los dos, la misma correccion va en los scripts sueltos via indices_centrados(), y hay 16 pruebas nuevas, una de ellas de regresion con los dos lados fijados por monkeypatch.
A70: 67 | B70: 7 | C70: F2 | D70: Anadir retro_holograma.py: retropropagar un holograma con el propagador que elijas | E70: Reconstruccion sobre dato ya registrado | F70: Media | G70: Hecho | H70: 28/08/2026 | I70: Commit 4939608. Los otros retro_*.py demuestran un propagador cada uno sobre un objeto sintetico y hacen la ida y la vuelta; este no demuestra ninguno: recibe un holograma que ya existe y lo lleva al plano del objeto llamando a CamposT.pipeline.propagar(), en vez de cargar una cuarta copia de los propagadores. USAR_ANGULAR / USAR_BLAS / USAR_MPASM: varios en True se comparan en la misma figura, sobre el mismo dato y la misma z, que es la unica forma honesta de compararlos. RECORTAR abre la imagen y deja arrastrar la ventana con el raton; imprime el radio del cono de difraccion z*tan(theta)/delta -534 px con 633 nm, 3.45 um y z = 20 mm- y avisa cuando la ROI se queda corta, pero recorta igual: es una decision del que mira, no una guarda. La extension decide la entrada: imagen -> intensidad medida, campo = sqrt(I), con la gemela encima; .npy -> campo complejo, y ahi la vuelta deshace la ida exactamente. GAMMA_GUARDADO deshace la gamma del PNG antes de la raiz: con los 0.6 de resultados/campos/ no solo falsea el contraste, mueve la distancia a la que enfoca la reconstruccion. Es el script con el que se atacaran los hologramas reales de la semana 11.
A71: 68 | B71: 7 | C71: F1 | D71: Anadir el modo mixto de objeto: amplitud y fase acopladas | E71: Objeto que absorbe y retarda | F71: Media | G71: Hecho | H71: 28/08/2026 | I71: Commit 66efe91. load_field tenia los dos extremos -'amplitud' con U0 = t y fase 0, y 'fase' con U0 = exp(i*d*t) y amplitud plana- pero no el caso general, que es el que modela una muestra real: U0 = t*exp(i*phase_depth*t). LA TRAMPA, escrita en el docstring y fijada en test_objeto_mixto.py: sobre un objeto BINARIO el modo es degenerado y phase_depth NO HACE NADA, porque queda 0 donde t=0 y exp(i*phase_depth) donde t=1, o sea el campo entero por una constante de modulo 1: una fase GLOBAL, que se cancela en |U|^2 y conmuta con la propagacion. Medido sobre usaf_like barriendo phase_depth de 0 a 2pi: contraste del holograma 2.129 y correlacion de la reconstruccion 0.725, las dos constantes hasta el ultimo decimal. usaf_like es binario, asi que el modo necesita escala de grises: resultados/campos/entrada_gris.png, el USAF suavizado a 219 niveles. scripts/mi_prueba.py exploro el parametro en linea (commit 1c335ba) y al 31/08 esta borrado en el arbol de trabajo, sin commitear.
... A76: 73 | B76: 8 | C76: F3 | D76: Preparar la hoja de parametros y el modulo que recibira las medidas | E76: Checklist de laboratorio + CamposT/montaje.py | F76: Alta | G76: Hecho | H76: 04/09/2026 | I76: Preparado el entregable de la tarea 17 antes de la visita al laboratorio, para que la media jornada rinda y no haga falta una segunda. DOS PIEZAS. docs/hoja_parametros_montaje.md es el checklist que se lleva en la mano: cada magnitud con sus unidades, la conversion a milimetros, por que la necesita el codigo, y tres avisos que salen de fallos ya medidos -que delta_x y delta_y se anoten por separado aunque parezcan iguales, porque Kf va por eje desde la tarea 61; que el rango alcanzable de z define la malla del barrido de la tarea 29; y que hay que preguntar si la camara aplica gamma, porque la tarea 69 midio que la gamma MUEVE la distancia a la que enfoca la reconstruccion, con un metodo para averiguarlo alli mismo si no consta: dos exposiciones conocidas, y si es lineal el nivel medio se duplica-. CamposT/montaje.py es el destino de los numeros, con TABLA1 y MONTAJE SEPARADOS. HALLAZGO QUE LO MOTIVA: el repo tenia TRES longitudes de onda conviviendo -632.8 nm en figura_escenario.py y exactitud.py, que es la Tabla 1 y esta bien; 633 nm en los cuatro retro_*.py; y 405 nm en comparacion.py y mi_holograma.py-. Entre 633 y 405 hay un 56 %, y lambda entra en z_lim, en Kf, en el radio del cono de difraccion y en la distancia de enfoque. DELTA = 3.45e-3 estaba repetido en siete archivos, sin verificar. Un parametro sin medir NO vale un numero: vale el centinela SinMedir, que revienta con ParametroSinMedir en cuanto entra en una cuenta -multiplicar, dividir, potencia, float(), int(), numpy y las propiedades derivadas: once vias probadas- y dice que magnitud falta y como se obtiene. Es la misma decision que _comprobar_ventana() y que el endurecimiento de sam(): fallar fuerte antes que devolver un numero creible que luego hay que tirar. Quedan 15 parametros PENDIENTES, que son los que traera la tarea 17. figura_escenario.py y exactitud.py ya leen de TABLA1 en vez de repetir literales, con los valores identicos comprobados. 23 pruebas nuevas en tests/test_montaje.py, una de ellas de regresion sobre la DECISION y no sobre la cuenta: falla si alguien rellena un hueco con un valor plausible mientras tanto. Suite de 299 a 322 en verde. PENDIENTE A PROPOSITO: retro_holograma.py y mi_holograma.py, que son los que atacaran hologramas reales, todavia no leen de MONTAJE. Conectarlos hoy los romperia -sus parametros estan sin medir- y son las dos piezas con las que se prueba antes de la semana 11; se conectan cuando vuelvan los numeros. comparacion.py se queda con su lambda propia: es un benchmark de tiempos y el tiempo no depende de lambda.
A77: 74 | B77: Receso | C77: F1 | D77: Anadir soporte de GPU a los cuatro barridos mi_prueba_* | E77: Los cuatro scripts corriendo en CPU y GPU + suite de paridad | F77: Media | G77: Hecho | H77: 11/09/2026 | I77: Hecha el 08/09, en la semana de receso. Los cuatro barridos puntuados de scripts/mi_prueba_*.py aceptan ahora DISPOSITIVO -auto, cpu o gpu- y DTYPE, con la politica de CamposT.backend: complex64 en GPU, complex128 en CPU, y las FASES siempre en float64. DE DONDE SALE EL DISENO: blas y mpasm ya tenian xp y dtype en la firma de su propagador y un bloque `backend` marcado y VACIO, asi que solo faltaba quien los eligiera. angular y dlhm no podian tocarse igual porque su implementacion de referencia esta copiada tal cual -angularSpectrum de pyDHM, y point_src + angular_spectrum de dlhm.py-, asi que reciben COPIA DE TRABAJO -espectro_angular, fuente_puntual- y la referencia se queda intacta. Es lo que el encabezado de esos mismos archivos manda hacer. MEDIDO sobre BenchmarkTarget 3000x4000, la misma corrida en las dos maquinas: dlhm 152.92 s -> 6.33 s (x24, 25 pasos), angular 16.54 -> 0.49 (x34), mpasm 45.95 -> 1.67 (x28), blas 9.19 -> 0.93 (x10). Las curvas del barrido salen IDENTICAS a los cuatro decimales que imprime la consola. EQUIVALENCIA contra la referencia de cada script, que ahora se imprime en cada corrida: 0.0 EXACTO en CPU/complex128 -misma aritmetica y misma biblioteca de FFT-, 6e-16 a 1.1e-12 en GPU/complex128 -cuFFT redondea distinto que pocketfft- y 2.5e-7 a 9.0e-7 en GPU/complex64. El caso de en medio es el que separa el DISPOSITIVO de la PRECISION: lo que se pierde arriba es la mantisa, no la tarjeta. La reduccion de correlacion() va en float64 aunque el campo venga en complex64: sobre 1.2e7 sumandos el error de float32 es del orden de lo que separa dos pasos del barrido, y el argmax se iria a un z equivocado. tests/test_gpu_mi_prueba.py, 54 pruebas; suite total de 360 a 414 en verde. LO QUE NO ARREGLA, y es lo importante: la tarjeta es una RTX 3050 Laptop de 4 GB, asi que con SOBREMUESTREO = None la malla que exige la geometria en dlhm sigue siendo 13312x13312 -1.42 GB POR ARRAY en complex64, y la cadena necesita varios a la vez- y NO cabe. Lo que complex64 compra es aproximadamente el DOBLE de recorte que en CPU: ~1700 px de lado contra ~1300. El callejon que documenta la tarea 27 sigue abierto, y la salida sigue siendo puntuar por nitidez. DOS COSAS QUE LAS PRUEBAS ENCONTRARON: sincronizar() no existia en los retro_*, sale de CamposT.backend, y la atribucion que se habia escrito era falsa; y la tolerancia de GPU/complex128 no podia ser 1e-12 porque dlhm da 1.1e-12. De paso, corregido el aviso de malla rectangular de blas y mpasm, que hablaba de los ejes cruzados de angularSpectrum cuando ninguno de los dos la usa: era copia-pega desde angular y contradecia al docstring del propio archivo.
A78: 75 | B78: 9 | C78: F1 | D78: Corregir el bug de ejes cruzados en mi_prueba_mpasm y anadir guarda de convencion de ejes | E78: Guarda de ejes en los sidecar + mpasm_minimo.py + montaje con datos medidos | F78: Alta | G78: Hecho | H78: 18/09/2026 | I78: Commit 4e0927c0e. _comprobar_con_el_sidecar() de mi_prueba_angular, _blas y _mpasm compara ahora tambien la CONVENCION DE EJES contra el .txt del holograma, no solo lambda y delta: angularSpectrum de pyDHM cruza dfx y dfy (cada eje con la longitud del OTRO), espectro_angular_bl y mpasm_bloques llevan cada uno el suyo; en malla cuadrada da igual, en rectangular son dos transformadas distintas y la vuelta no deshace la ida, sin lanzar ni avisar. mi_prueba_mpasm era la victima: EJES_CRUZADOS = True describia al holograma de su RUTA y no a mpasm_bloques, y silenciaba la guarda. MEDIDO sobre la misma configuracion (mismo holograma, mismo propagador, misma metrica, cruzando solo las frecuencias): con cada eje su longitud, foco 16.500 mm, corr 0.8089, altura 0.0161; con los ejes cruzados (los del .txt), foco 10.000 mm, corr 0.8615, altura 0.0792, para un holograma hecho a 10.000 mm. Ahora EJES_CRUZADOS = False y RUTA apunta a blas/z0200.000.npy (BL-ASM, ejes en su sitio): enfoca en 200.000 mm con corr 0.9132, igual al docstring. Sobre el .png de al lado (sin fase) la curva no tiene pico (0.6717 a 0.6744 entre 199.80 y 200.20, subiendo al final): la gemela pesa tanto como la imagen real. retro_mpasm: Kf POR EJE en vez del min() de los dos, porque Kf va como 1/sqrt(N) y el eje corto pide mas compresion que el largo. Contrastado ademas que mpasm_minimo.mpasm (nuevo, el propagador de Zhao solo) y mpasm_bloques son el mismo algoritmo: 1.7e-15 de diferencia maxima, correlacion 1.000000000000 en CPU/complex128. montaje.py: lambda, pinhole y los dos pasos de pixel y L pasan de SinMedir a valores medidos (insumo de la tarea 17). Nuevos scripts/barrido_foco.py (autofoco con Tamura, Pearson y SSIM) y scripts/propagar_imagen.py, y tests/test_sidecar_ejes.py + tests/test_kf_por_eje_scripts.py. 465 passed, 4 skipped.
A79: 76 | B79: 9 | C79: F1 | D79: Encadenar el SSIM de CPU con la propagacion GPU en barrido_foco | E79: Barrido de foco mas rapido sin perder precision | F79: Media | G79: Hecho | H79: 18/09/2026 | I79: Commit e1580599b0. SSIM es la unica de las tres metricas de barrido_foco.py que corre en CPU (skimage no tiene version GPU) y mientras se calcula la tarjeta esta parada. El bucle ahora LANZA la propagacion del paso i (mpasm() vuelve enseguida, CuPy encola asincrono) y, mientras la GPU la hace, la CPU cierra el SSIM del paso i-1: el costo por z pasa de la SUMA de los dos lados al MAYOR. No hacen falta hilos, el solapamiento lo da el driver (basta con no sincronizar entre el lanzamiento y el trabajo de CPU); desaparece el cp.cuda.Stream.null.synchronize() explicito. MEDIDO sobre 62 retropropagaciones, BORDE_PX = 1000, Z_REAL = 60, RTX 3050 Laptop, serie vs solapado: con S=1, 42.2 s -> 27.9 s (34% de ahorro, 391->157 ms/z en la GPU); con S=2, 112.8 s -> 102.0 s (10%, 1503->1333 ms/z). No llega al techo: SSIM cuesta ~17 s en las cuatro corridas y con S=1 se esconden 14.3 de esos 17 (86%), con S=2 solo 10.8 (63%) aun sobrando sitio para esconderlo entero; queda como hipotesis SIN MEDIR que la copia a CPU y el reparto del pool de CuPy comparten stream con la propagacion. Las curvas salen IDENTICAS bit a bit contra la version en serie en los dos valores de S (comprobado clave por clave del .npz), porque esto mueve el reloj y no los numeros; se escriben por INDICE y no con append, porque el paso i-1 se cierra una vuelta mas tarde que el i. Dos constantes nuevas: EN_CPU (que metricas viven en CPU) y SOLAPAR (apaga el encadenado para remedir en serie), con SOLAPANDO desactivandolo solo cuando no hay GPU que adelantar o no hay metrica de CPU que esconder. Probada tambien la ruta sin tarjeta (GPU=False, malla 512x512): cae a serie y las tres metricas aciertan el foco. 465 passed, 4 skipped.
A80: 77 | B80: 10 | C80: F1 | D80: Anadir ROI arrastrable y bloques de memoria a barrido_foco / mpasm_minimo | E80: Barrido de foco enfocable a una region, sin desbordar memoria | F80: Media | G80: En curso | H80: 25/09/2026 | I80: SIN COMMITEAR al 22/09 (arbol de trabajo). ROI en barrido_foco.py: mpasm(ventana=...) evalua la salida solo en una region del plano en vez de recortar el holograma de entrada, para no perder los angulos altos del cono ni meter anillos de corte en la metrica; ROI = None (borde de siempre), True (se arrastra con el raton sobre |U0|^2) o una tupla (X0,Y0,ANCHO,ALTO). Avisa hasta que z el margen sigue tapando los anillos del borde (z_cubre). mpasm_minimo.mpasm gana el parametro ventana (calcula solo esa porcion de la malla de salida; la entrada sigue siendo el holograma entero y Kf no cambia) y arma la funcion de transferencia POR BLOQUES de filas en vez de entera: con 3000x4000 y s=3 los temporales enteros pasaban de 4 GB encima de F, y en Windows el driver no fallaba, desbordaba a RAM y cada z se arrastraba; el paso de bloque es ~64 MB de float64. La mascara arg>0 se aplica por producto y no con indexado booleano, porque el indexado obliga a CuPy a sincronizar y rompia el encadenado SOLAPAR de la tarea 76. fasor() ahora escribe cos/sin directo en el dtype de trabajo en vez de pasar por complex128 (el doble de memoria). De paso, en los parametros del script S baja de 2 a 1 y SOLAPAR de True a False, para volver a medir en serie.
A81: 78 | B81: 10 | C81: F2 | D81: Implementar el MPASM con la onda esferica exacta para DLHM (CamposT/dlhm.py) | E81: CamposT/dlhm.py + tests/test_dlhm.py + scripts/verif_dlhm_esferico.py | F81: Alta | G81: Hecho | H81: 25/09/2026 | I81: Commit 17b6e2f510. MPASM con la onda esferica EXACTA en los dos sentidos, sin aproximacion paraxial: CamposT/dlhm.py, con holograma() para simular y Reconstructor/reconstruir() para reconstruir; el Reconstructor calcula el espectro del sensor una sola vez para todo un barrido de z. La parte parabolica de e^{ikr}/r va DENTRO de las matrices de la DFT con integrales de Fresnel (ventana_chirp: la DFT exacta de una entrada de banda limitada por un chirp sin muestrear) y el residuo no paraxial punto a punto; la rejilla de frecuencias sale de la geometria, con banda mas ancha que 1/delta (Kf < 1: expansion, no compresion), y se reconstruye c - 1 (con c, la referencia truncada en el borde del sensor bajaba la corr de 0.90 a 0.27). SUPERA LA RECOMENDACION (i) DE LA TAREA 24: el escalado z_eq en la malla delta/M solo se habia validado con objetos lisos de 6 a 30 um; con detalle de ~1.25 um su ida contra Rayleigh-Sommerfeld directo da error 0.47 en el eje, 0.65 a 5.7 grados y 0.89 a 12.4, y la exacta 3.6e-6 en los tres. Sensor entero (N = 3000, borde a 15.3 grados): corr con el objeto 0.969 en la ventana entera (1.0000 hasta 3 grados, 0.925 en la esquina) contra 0.683 del escalado; la misma rejilla sin las ventanas de Fresnel da 0.516, y en N = 2048 entre 0.42 y 0.946 segun el periodo P: acierta por geometria, no por construccion. Coste por z igual al escalado: 0.36 frente a 0.33 s en N = 3000; con 3000x4000 px son 5200x7712 frecuencias (306 MB en complex64), 9.8 s una vez y 0.56 s por z en la RTX 3050. Autofoco por nitidez sobre un holograma de INTENSIDAD del BenchmarkTarget a z = 3 mm: la exacta encuentra 3.0005 mm y el escalado se va al extremo del barrido. Contrastada con reconstruir() de mi_prueba_dlhm (la cadena de Carlos): corr 0.993 con malla PAR y remuestreo de banda limitada; con la malla impar que da malla_remuestreada (2027) solo 0.875, porque su linspace no pasa por f = 0 y desplaza ~1 um. tests/test_dlhm.py: 21 pruebas, 10 de 10 mutaciones detectadas; scripts/verif_dlhm_esferico.py reproduce las cifras; scipy pasa a dependencia. 486 passed, 4 skipped. Fusionada a main el 27/09. Cierra las tareas 25 y 27, decidido el 27/09. DEUDAS ABIERTAS: la malla impar de malla_remuestreada sigue sin corregir; la imagen gemela no se suprime; no se modela la integracion del pixel; la ida del sensor entero tarda 34 s en GPU; y hay que revisar la diapositiva 9 (Kf) y el PDF de la tarea 24.
A82: 79 | B82: 11 | C82: F2 | D82: Portar la seleccion de foco de barrido_foco a mi_prueba_dlhm (motores exacto y de Carlos) y anadir el modelo de Lopera como segundo simulador | E82: scripts/mi_prueba_dlhm.py + tests/test_mi_prueba_dlhm_seleccion.py + arreglo de CamposT/dlhm.py | F82: Alta | G82: Hecho | H82: 02/10/2026 | I82: Commits 4e08e49050 (CamposT/dlhm.py) y dfe6fe7a27. mi_prueba_dlhm.py elige el foco con los parametros de seleccion de barrido_foco (Tamura, Pearson y SSIM sobre la misma reconstruccion, grueso + fino, ROI o cuarto central, tabla, curvas.npz y dos figuras; metricas copiadas con prueba ast) y dos motores: exacto (CamposT.dlhm, holograma entero) y de Carlos (reconstruir() sobre el recorte: hay que dividir por |U0|^2 -0.84 frente a 0.21-, tomar la huella del 1/M central y usar un ROI cuadrado). BenchmarkTarget simulado 3000x4000 a z = 3 mm: exacto 3.0000 en las tres metricas, tambien con Z_REAL a medio paso de la rejilla; Carlos (ROI 1024) a 2 um; objeto de fase, -Tamura a 1 um. El ~0.03 del script viejo era la geometria de referencia_a_escala(): +0.051 frente a -0.731 con la huella. Arreglado de paso holograma() de CamposT/dlhm.py: el soporte recortaba la frecuencia del otro eje a 1/lambda y pedia 86.7 GB con 3000x4000; ahora 40 s en GPU y RS sigue en 3.7e-6. SIMULADOR = 'lopera': el modelo de Lopera et al. 2024 (su dlhm() copiada literal, verificada bit a bit contra su codigo): su holograma reconstruido exacto enfoca +14 a +20 um fuera de Z_REAL; sin Brown-Conrady, envolvente ni 8 bits sigue (+16 a +27 um): es su nucleo paraxial (contra la ida exacta, 1.00000 con objeto liso y 0.895 con detalle fino). 49 pruebas nuevas; suite 551 passed.

Sheet Hitos
A1: Fechas institucionales confirmadas (Directrices 2026-2)
A3: Fecha | B3: Semana | C3: Actividad | D3: Peso en la nota
A4: 27 de julio de 2026 | B4: 3 | C4: Anteproyecto - documento escrito | D4: 10 % (con sustentacion)
A5: 3 de agosto de 2026 | B5: 4 | C5: Anteproyecto - sustentacion oral | D5: 10 % (con documento)
A6: 31 de agosto de 2026 | B6: 8 | C6: Exposicion informe de avance 1 | D6: 5 %
A7: 19 de octubre de 2026 | B7: 14 | C7: Exposicion informe de avance 2 | D7: 5 %
A8: 30 de octubre de 2026 | B8: 15 | C8: Limite de entrega del informe final con carta de aval | D8: -
A9: Hasta el 20 de noviembre de 2026 | B9: 18 | C9: Defensa o presentacion publica ante jurados | D9: 45 %
A10: Hasta el 20 de noviembre de 2026 | B10: 18 | C10: Desarrollo del trabajo y sustentacion (asesor) | D10: 35 %
A11: 9 y 10 de diciembre de 2026 | B11: - | C11: Ceremonia de grados | D11: -
A13: Nota: la Opcion 1 (con opcion a mencion de honor) exigiria entregar el informe final el 13 de octubre (semana 13) y defender antes del 6 de noviembre. Este cronograma sigue la Opcion 2.
